{
  "doc_name": "พิเชษฐ์_เชื้อเมืองพาน_สมาชิกสภาผู้แทนราษฎร_(ส.ส.)_กรณีพ้นจากตำแหน่ง_12_มิ.ย._2566.json",
  "page_number": 18,
  "page_index": 17,
  "total_pages": 37,
  "page_type": "investments",
  "is_continuation": false,
  "is_extra_page": false,
  "matched_template_page": null,
  "content": "- ลับ -\nหน้า 11\nรายละเอียดประกอบรายการเงินลงทุน\nผู้ยื่นบัญชี จำนวนเงินรวม 124,500 บาท (ยกไปกรอกในบัญชีฯ หน้า 7)\nคู่สมรส จำนวนเงินรวม 2,125,000 บาท (ยกไปกรอกในบัญชีฯ หน้า 7)\nบุตรที่ยังไม่บรรลุนิติภาวะ จำนวนเงินรวม บาท (ยกไปกรอกในบัญชีฯ หน้า 7)\nลำดับ ประเภทเงินลงทุน จำนวนหน่วย วัน / เดือน / ปี มูลค่า ณ วันที่มีหน้าที่แสดง ของ\nที่ ที่ได้มา รายทรัพย์สินและหนี้สิน ผย. คส. บ.\n1 หุ้นใน บจ.ด็อกเตอร์กระท่อม 4,900 4 มีค.64 122,500\n2 หุ้นใน บจ.ดิยกเตอร์กระท่อม 5,000 4 มีค. 64 125,000\n3 ลงทุนด้วยเงินร้านอดามาส จิวเวอร์รี่ 3 กย.61 2,000,000 1\n4 หุ้น DRACO 2,000 2,000 /\n* หมายเหตุ ผย. = ผู้ยื่นบัญชี , คส. = คู่สมรส , บ. = บุตรที่ยังไม่บรรลุนิติภาวะ\nลงชื่อ ผู้ยื่นบัญชี\n- ลับ -",
  "lines": [
    {
      "text": "- ลับ -",
      "y": 0.166,
      "x": 4.088
    },
    {
      "text": "หน้า 11",
      "y": 0.577,
      "x": 7.095
    },
    {
      "text": "รายละเอียดประกอบรายการเงินลงทุน",
      "y": 0.771,
      "x": 4.074
    },
    {
      "text": "124,500",
      "y": 1.048,
      "x": 3.447
    },
    {
      "text": "ผู้ยื่นบัญชี จำนวนเงินรวม",
      "y": 1.085,
      "x": 2.192
    },
    {
      "text": "บาท (ยกไปกรอกในบัญชีฯ หน้า 7)",
      "y": 1.133,
      "x": 5.753
    },
    {
      "text": "2,125,000",
      "y": 1.304,
      "x": 3.543
    },
    {
      "text": "คู่สมรส จำนวนเงินรวม",
      "y": 1.348,
      "x": 2.256
    },
    {
      "text": "บาท (ยกไปกรอกในบัญชีฯ หน้า 7)",
      "y": 1.384,
      "x": 5.754
    },
    {
      "text": "บุตรที่ยังไม่บรรลุนิติภาวะ จำนวนเงินรวม",
      "y": 1.582,
      "x": 1.812
    },
    {
      "text": "บาท (ยกไปกรอกในบัญชีฯ หน้า 7)",
      "y": 1.639,
      "x": 5.758
    },
    {
      "text": "ลำดับ",
      "y": 1.993,
      "x": 0.687
    },
    {
      "text": "ของ",
      "y": 2.032,
      "x": 7.518
    },
    {
      "text": "วัน / เดือน / ปี",
      "y": 2.037,
      "x": 5.047
    },
    {
      "text": "มูลค่า ณ วันที่มีหน้าที่แสดง",
      "y": 2.052,
      "x": 6.325
    },
    {
      "text": "ประเภทเงินลงทุน",
      "y": 2.117,
      "x": 2.288
    },
    {
      "text": "จำนวนหน่วย",
      "y": 2.122,
      "x": 4.069
    },
    {
      "text": "ที่",
      "y": 2.169,
      "x": 0.694
    },
    {
      "text": "ที่ได้มา",
      "y": 2.214,
      "x": 5.042
    },
    {
      "text": "รายทรัพย์สินและหนี้สิน",
      "y": 2.236,
      "x": 6.318
    },
    {
      "text": "ผย.",
      "y": 2.299,
      "x": 7.207
    },
    {
      "text": "คส.",
      "y": 2.304,
      "x": 7.513
    },
    {
      "text": "บ.",
      "y": 2.309,
      "x": 7.813
    },
    {
      "text": "1",
      "y": 2.497,
      "x": 0.694
    },
    {
      "text": "หุ้นใน บจ.ด็อกเตอร์กระท่อม",
      "y": 2.516,
      "x": 2.287
    },
    {
      "text": "4,900",
      "y": 2.535,
      "x": 4.057
    },
    {
      "text": "4 มีค.64",
      "y": 2.54,
      "x": 5.049
    },
    {
      "text": "122,500",
      "y": 2.558,
      "x": 6.332
    },
    {
      "text": "2",
      "y": 2.756,
      "x": 0.693
    },
    {
      "text": "หุ้นใน บจ.ดิยกเตอร์กระท่อม",
      "y": 2.773,
      "x": 2.287
    },
    {
      "text": "5,000",
      "y": 2.79,
      "x": 4.055
    },
    {
      "text": "4 มีค. 64",
      "y": 2.802,
      "x": 5.044
    },
    {
      "text": "125,000",
      "y": 2.812,
      "x": 6.33
    },
    {
      "text": "3",
      "y": 3.018,
      "x": 0.688
    },
    {
      "text": "ลงทุนด้วยเงินร้านอดามาส จิวเวอร์รี่",
      "y": 3.03,
      "x": 2.289
    },
    {
      "text": "3 กย.61",
      "y": 3.059,
      "x": 5.033
    },
    {
      "text": "2,000,000",
      "y": 3.073,
      "x": 6.304
    },
    {
      "text": "1",
      "y": 3.095,
      "x": 7.532
    },
    {
      "text": "4",
      "y": 3.269,
      "x": 0.687
    },
    {
      "text": "หุ้น DRACO",
      "y": 3.287,
      "x": 2.288
    },
    {
      "text": "2,000",
      "y": 3.308,
      "x": 4.061
    },
    {
      "text": "2,000",
      "y": 3.332,
      "x": 6.318
    },
    {
      "text": "/",
      "y": 3.345,
      "x": 7.222
    },
    {
      "text": "* หมายเหตุ ผย. = ผู้ยื่นบัญชี , คส. = คู่สมรส , บ. = บุตรที่ยังไม่บรรลุนิติภาวะ",
      "y": 9.98,
      "x": 5.985
    },
    {
      "text": "ลงชื่อ",
      "y": 10.606,
      "x": 3.995
    },
    {
      "text": "ผู้ยื่นบัญชี",
      "y": 10.658,
      "x": 7.062
    },
    {
      "text": "- ลับ -",
      "y": 10.87,
      "x": 4.043
    }
  ]
}