{
  "doc_name": "เชิงชาย_ชาลีรินทร์_สมาชิกสภาผู้แทนราษฎร_(ส.ส.)_กรณีพ้นจากตำแหน่ง_15_มี.ค._2566.json",
  "page_number": 15,
  "page_index": 14,
  "total_pages": 25,
  "page_type": "loans_given",
  "is_continuation": false,
  "is_extra_page": false,
  "matched_template_page": null,
  "content": "- ลับ -\nหน้า 12\nรายละเอียดประกอบรายการเงินให้กู้ยืม\nผู้ยื่นบัญชี จำนวนเงินรวม บาท (ยกไปกรอกในบัญชีฯ หน้า 7)\nคู่สมรสจำนวนเงินรวม บาท (ยกไปกรอกในบัญชีฯ หน้า 7)\nบุตรที่ยังไม่บรรลุนิติภาวะ จำนวนเงินรวม บาท (ยกไปกรอกในบัญชีฯ หน้า 7)\nลำดับ ชื่อและชื่อสกุล ที่อยู่/อาชีพ ผู้กู้ยืม วัน/เดือน/ปี จำนวนเงิน ของ\nที่ ผู้กู้ยืม ที่ให้กู้ยืม จำนวนเงินกู้ ยอดหนี้คงเหลือ ผย. คส. บ.\nตามสัญญา\n3\n3\nหมายเหตุ ผย. = ผู้ยื่นบัญชี , คส. = คู่สมรส , บ. = บุตรที่ยังไม่บรรลุนิติภาวะ\nลงชื่อ ผู้ยื่นบัญชี\n- ลับ -",
  "lines": [
    {
      "text": "- ลับ -",
      "y": 0.288,
      "x": 4.301
    },
    {
      "text": "หน้า 12",
      "y": 0.655,
      "x": 7.108
    },
    {
      "text": "รายละเอียดประกอบรายการเงินให้กู้ยืม",
      "y": 0.853,
      "x": 4.279
    },
    {
      "text": "ผู้ยื่นบัญชี จำนวนเงินรวม",
      "y": 1.169,
      "x": 2.53
    },
    {
      "text": "บาท (ยกไปกรอกในบัญชีฯ หน้า 7)",
      "y": 1.186,
      "x": 5.332
    },
    {
      "text": "คู่สมรสจำนวนเงินรวม",
      "y": 1.411,
      "x": 2.552
    },
    {
      "text": "บาท (ยกไปกรอกในบัญชีฯ หน้า 7)",
      "y": 1.416,
      "x": 4.855
    },
    {
      "text": "บุตรที่ยังไม่บรรลุนิติภาวะ จำนวนเงินรวม",
      "y": 1.645,
      "x": 2.16
    },
    {
      "text": "บาท (ยกไปกรอกในบัญชีฯ หน้า 7)",
      "y": 1.66,
      "x": 5.337
    },
    {
      "text": "จำนวนเงิน",
      "y": 1.985,
      "x": 5.835
    },
    {
      "text": "ของ",
      "y": 2.001,
      "x": 7.402
    },
    {
      "text": "ลำดับ",
      "y": 2.057,
      "x": 0.995
    },
    {
      "text": "ชื่อและชื่อสกุล",
      "y": 2.065,
      "x": 1.893
    },
    {
      "text": "วัน/เดือน/ปี",
      "y": 2.067,
      "x": 4.292
    },
    {
      "text": "ที่อยู่/อาชีพ ผู้กู้ยืม",
      "y": 2.132,
      "x": 3.232
    },
    {
      "text": "จำนวนเงินกู้",
      "y": 2.174,
      "x": 5.32
    },
    {
      "text": "ที่",
      "y": 2.235,
      "x": 1.009
    },
    {
      "text": "ยอดหนี้คงเหลือ",
      "y": 2.249,
      "x": 6.439
    },
    {
      "text": "ที่ให้กู้ยืม",
      "y": 2.252,
      "x": 4.297
    },
    {
      "text": "ผู้กู้ยืม",
      "y": 2.257,
      "x": 1.888
    },
    {
      "text": "ผย.",
      "y": 2.276,
      "x": 7.113
    },
    {
      "text": "คส.",
      "y": 2.276,
      "x": 7.401
    },
    {
      "text": "บ.",
      "y": 2.28,
      "x": 7.675
    },
    {
      "text": "ตามสัญญา",
      "y": 2.354,
      "x": 5.308
    },
    {
      "text": "3",
      "y": 4.166,
      "x": 0.439
    },
    {
      "text": "3",
      "y": 7.329,
      "x": 0.44
    },
    {
      "text": "หมายเหตุ ผย. = ผู้ยื่นบัญชี , คส. = คู่สมรส , บ. = บุตรที่ยังไม่บรรลุนิติภาวะ",
      "y": 9.329,
      "x": 6.132
    },
    {
      "text": "ลงชื่อ",
      "y": 10.158,
      "x": 4.241
    },
    {
      "text": "ผู้ยื่นบัญชี",
      "y": 10.176,
      "x": 6.693
    },
    {
      "text": "- ลับ -",
      "y": 10.401,
      "x": 4.275
    }
  ]
}