{
  "doc_name": "อนุสรณ์_ปั้นทอง_สมาชิกสภาผู้แทนราษฎร_(ส.ส.)_กรณีพ้นจากตำแหน่ง_12_มิ.ย._2566.json",
  "page_number": 26,
  "page_index": 25,
  "total_pages": 37,
  "page_type": "vehicles",
  "is_continuation": false,
  "is_extra_page": false,
  "matched_template_page": null,
  "content": ". - ลับ -\nหน้า 15\nรายละเอียดประกอบรายการยานพาหนะ\nผู้ยื่นบัญชี รถยนต์ 1 คัน รถจักรยานยนต์ คัน เรือยนต์ .......... ลำ เครื่องบิน ............ ลำ\nมูลค่ารวม 988,000 บาท (ยกไปกรอกในบัญชีฯ หน้า 7)\nคู่สมรส รถยนต์ 5 คัน รถจักรยานยนต์ คัน เรือยนต์ ลำ เครื่องบิน, ลำ\nมูลค่ารวม 6:030,000 บาท (ยกไปกรอกในบัญชีฯ หน้า 7)\nบุตรที่ยังไม่บรรลุนิติภาวะ รถยนต์ คัน รถจักรยานยนต์ คัน เรือยนต์ ลำ เครื่องบิน ... .. ลำ\nมูลค่ารวม บาท (ยกไปกรอกในบัญชีฯ หน้า 7)\nลำดับ ประเภท หมายเลข จังหวัด วัน / เดือน / ปี มูลค่าปัจจุบัน ของ\nที่ ทะเบียน ที่ได้มา (โดยประมาณ) ผย. คส. บ.\n1 รถยนต์บรรทุกส่วนบุคคล 3ฒจ- กทม. 9 ต.ค. 2542 100,000\nC (เดิม ลบ-7157) 5791\n2 รถยนต์นั่งส่วนบุคคล ฮิน-5655 กทม. 6 พ.ค. 2554 700,000\n3 รถยนต์นั่งส่วนบุคคล 2กค-5655 กทม. 3 ก.ย. 2556 570.000\n4 รถยนต์นั่งส่วนบุคคล ภษ-345 กทม. 20 ส.ค. 2556 988.000\n5 รถยนต์นั่งส่วนบุคคล 8กล- กทม. 16 ต.ค.2563 560.000\n(จากป้ายแดง ณ-7869) 5655\n6 รถยนต์นั่งส่วนบุคคล 3ขฉ-5655 กทม. 22 พ.ย.2565 4.100.000\nC\nหมายเหตุ ผย. = ผู้ยื่นบัญชี , คส. = คู่สมรส , บ. = บุตรที่ยังไม่บรรลุนิติภาวะ\nลงชื่อ ผู้ยื่นบัญชี\nอนุสรณ์ ปันทอง\n- ลับ -",
  "lines": [
    {
      "text": ".",
      "y": 0.511,
      "x": 0.33
    },
    {
      "text": "- ลับ -",
      "y": 0.575,
      "x": 4.138
    },
    {
      "text": "หน้า 15",
      "y": 0.962,
      "x": 7.159
    },
    {
      "text": "รายละเอียดประกอบรายการยานพาหนะ",
      "y": 1.198,
      "x": 4.128
    },
    {
      "text": "1",
      "y": 1.581,
      "x": 2.613
    },
    {
      "text": "คัน รถจักรยานยนต์",
      "y": 1.584,
      "x": 3.551
    },
    {
      "text": "ผู้ยื่นบัญชี รถยนต์",
      "y": 1.585,
      "x": 1.863
    },
    {
      "text": "คัน เรือยนต์ ..........",
      "y": 1.589,
      "x": 5.048
    },
    {
      "text": "ลำ เครื่องบิน",
      "y": 1.598,
      "x": 6.477
    },
    {
      "text": "............ ลำ",
      "y": 1.606,
      "x": 7.306
    },
    {
      "text": "988,000",
      "y": 1.888,
      "x": 3.244
    },
    {
      "text": "มูลค่ารวม",
      "y": 1.897,
      "x": 2.223
    },
    {
      "text": "บาท (ยกไปกรอกในบัญชีฯ หน้า 7)",
      "y": 1.905,
      "x": 5.82
    },
    {
      "text": "คัน รถจักรยานยนต์",
      "y": 2.175,
      "x": 3.596
    },
    {
      "text": "คัน เรือยนต์",
      "y": 2.181,
      "x": 5.142
    },
    {
      "text": "คู่สมรส รถยนต์ 5",
      "y": 2.183,
      "x": 2.109
    },
    {
      "text": "ลำ เครื่องบิน,",
      "y": 2.184,
      "x": 6.48
    },
    {
      "text": "ลำ",
      "y": 2.202,
      "x": 7.553
    },
    {
      "text": "มูลค่ารวม 6:030,000",
      "y": 2.478,
      "x": 2.716
    },
    {
      "text": "บาท (ยกไปกรอกในบัญชีฯ หน้า 7)",
      "y": 2.495,
      "x": 5.817
    },
    {
      "text": "คัน รถจักรยานยนต์",
      "y": 2.76,
      "x": 3.505
    },
    {
      "text": "บุตรที่ยังไม่บรรลุนิติภาวะ รถยนต์",
      "y": 2.766,
      "x": 1.457
    },
    {
      "text": "คัน เรือยนต์",
      "y": 2.766,
      "x": 5.076
    },
    {
      "text": "ลำ เครื่องบิน ...",
      "y": 2.769,
      "x": 6.452
    },
    {
      "text": ".. ลำ",
      "y": 2.792,
      "x": 7.478
    },
    {
      "text": "มูลค่ารวม",
      "y": 3.07,
      "x": 2.218
    },
    {
      "text": "บาท (ยกไปกรอกในบัญชีฯ หน้า 7)",
      "y": 3.076,
      "x": 5.312
    },
    {
      "text": "ลำดับ",
      "y": 3.536,
      "x": 0.731
    },
    {
      "text": "วัน / เดือน / ปี",
      "y": 3.547,
      "x": 5.053
    },
    {
      "text": "หมายเลข",
      "y": 3.556,
      "x": 3.269
    },
    {
      "text": "ของ",
      "y": 3.567,
      "x": 7.278
    },
    {
      "text": "มูลค่าปัจจุบัน",
      "y": 3.569,
      "x": 6.178
    },
    {
      "text": "จังหวัด",
      "y": 3.652,
      "x": 4.109
    },
    {
      "text": "ประเภท",
      "y": 3.658,
      "x": 1.931
    },
    {
      "text": "ที่",
      "y": 3.743,
      "x": 0.737
    },
    {
      "text": "ที่ได้มา",
      "y": 3.759,
      "x": 5.043
    },
    {
      "text": "ทะเบียน",
      "y": 3.764,
      "x": 3.274
    },
    {
      "text": "(โดยประมาณ)",
      "y": 3.779,
      "x": 6.188
    },
    {
      "text": "ผย.",
      "y": 3.823,
      "x": 7.011
    },
    {
      "text": "คส.",
      "y": 3.827,
      "x": 7.308
    },
    {
      "text": "บ.",
      "y": 3.832,
      "x": 7.609
    },
    {
      "text": "รถยนต์บรรทุกส่วนบุคคล",
      "y": 4.038,
      "x": 1.766
    },
    {
      "text": "9 ต.ค. 2542",
      "y": 4.039,
      "x": 5.058
    },
    {
      "text": "3ฒจ-",
      "y": 4.04,
      "x": 3.264
    },
    {
      "text": "กทม.",
      "y": 4.057,
      "x": 4.113
    },
    {
      "text": "100,000",
      "y": 4.058,
      "x": 6.454
    },
    {
      "text": "1",
      "y": 4.147,
      "x": 0.734
    },
    {
      "text": "(เดิม ลบ-7157)",
      "y": 4.265,
      "x": 1.535
    },
    {
      "text": "5791",
      "y": 4.267,
      "x": 3.265
    },
    {
      "text": "C",
      "y": 4.368,
      "x": 0.362
    },
    {
      "text": "รถยนต์นั่งส่วนบุคคล",
      "y": 4.492,
      "x": 1.636
    },
    {
      "text": "6 พ.ค. 2554",
      "y": 4.506,
      "x": 5.048
    },
    {
      "text": "ฮิน-5655",
      "y": 4.508,
      "x": 3.269
    },
    {
      "text": "กทม.",
      "y": 4.516,
      "x": 4.109
    },
    {
      "text": "700,000",
      "y": 4.52,
      "x": 6.448
    },
    {
      "text": "2",
      "y": 4.533,
      "x": 0.733
    },
    {
      "text": "รถยนต์นั่งส่วนบุคคล",
      "y": 4.791,
      "x": 1.662
    },
    {
      "text": "2กค-5655",
      "y": 4.794,
      "x": 3.279
    },
    {
      "text": "3 ก.ย. 2556",
      "y": 4.805,
      "x": 5.056
    },
    {
      "text": "กทม.",
      "y": 4.816,
      "x": 4.1
    },
    {
      "text": "570.000",
      "y": 4.819,
      "x": 6.447
    },
    {
      "text": "3",
      "y": 4.831,
      "x": 0.735
    },
    {
      "text": "รถยนต์นั่งส่วนบุคคล",
      "y": 5.092,
      "x": 1.64
    },
    {
      "text": "20 ส.ค. 2556",
      "y": 5.104,
      "x": 5.043
    },
    {
      "text": "ภษ-345",
      "y": 5.109,
      "x": 3.27
    },
    {
      "text": "กทม.",
      "y": 5.109,
      "x": 4.11
    },
    {
      "text": "988.000",
      "y": 5.114,
      "x": 6.437
    },
    {
      "text": "4",
      "y": 5.124,
      "x": 0.728
    },
    {
      "text": "รถยนต์นั่งส่วนบุคคล",
      "y": 5.385,
      "x": 1.633
    },
    {
      "text": "16 ต.ค.2563",
      "y": 5.396,
      "x": 5.051
    },
    {
      "text": "8กล-",
      "y": 5.399,
      "x": 3.27
    },
    {
      "text": "560.000",
      "y": 5.412,
      "x": 6.436
    },
    {
      "text": "กทม.",
      "y": 5.415,
      "x": 4.11
    },
    {
      "text": "5",
      "y": 5.507,
      "x": 0.732
    },
    {
      "text": "(จากป้ายแดง ณ-7869)",
      "y": 5.604,
      "x": 1.739
    },
    {
      "text": "5655",
      "y": 5.63,
      "x": 3.274
    },
    {
      "text": "รถยนต์นั่งส่วนบุคคล",
      "y": 5.851,
      "x": 1.64
    },
    {
      "text": "3ขฉ-5655",
      "y": 5.852,
      "x": 3.264
    },
    {
      "text": "22 พ.ย.2565",
      "y": 5.862,
      "x": 5.041
    },
    {
      "text": "กทม.",
      "y": 5.876,
      "x": 4.103
    },
    {
      "text": "4.100.000",
      "y": 5.88,
      "x": 6.376
    },
    {
      "text": "6",
      "y": 5.889,
      "x": 0.727
    },
    {
      "text": "C",
      "y": 7.537,
      "x": 0.373
    },
    {
      "text": "หมายเหตุ ผย. = ผู้ยื่นบัญชี , คส. = คู่สมรส , บ. = บุตรที่ยังไม่บรรลุนิติภาวะ",
      "y": 9.431,
      "x": 6.066
    },
    {
      "text": "ลงชื่อ",
      "y": 10.441,
      "x": 4.039
    },
    {
      "text": "ผู้ยื่นบัญชี",
      "y": 10.471,
      "x": 7.095
    },
    {
      "text": "อนุสรณ์ ปันทอง",
      "y": 10.637,
      "x": 5.475
    },
    {
      "text": "- ลับ -",
      "y": 11.14,
      "x": 4.082
    }
  ]
}