{
  "doc_name": "ณัฐพงษ์_สุปริยศิลป์_สมาชิกสภาผู้แทนราษฎร_(ส.ส.)_กรณีพ้นจากตำแหน่ง_23_มิ.ย._2566.json",
  "page_number": 24,
  "page_index": 23,
  "total_pages": 38,
  "page_type": "buildings",
  "is_continuation": false,
  "is_extra_page": false,
  "matched_template_page": null,
  "content": "- ลับ -\nหน้า 14\nรายละเอียดประกอบรายการโรงเรือนและสิ่งปลูกสร้าง\nผู้ยื่นบัญชี จำนวน. 5 หลัง จำนวนเงินรวม 2,600,000.00 บาท (ยกไปกรอกในบัญชีฯ หน้า 7)\nคู่สมรส จำนวน - หลัง จำนวนเงินรวม บาท (ยกไปกรอกในบัญชีฯ หน้า 7)\nบุตรที่ยังไม่บรรลุนิติภาวะ จำนวน \" หลัง จำนวนเงินรวม บาท (ยกไปกรอกในบัญชีฯ หน้า 7)\nลำดับ ประเภท / ที่ตั้ง ปลูกสร้างบน ว/ด/ป มูลค่าปัจจุบัน ของ\nที่ ลักษณะ เลขที่ เอกสารสิทธิ์ ที่ได้มา การได้มา (โดยประมาณ)\nสิ่งปลูกสร้าง ตำบล/อำเภอ/จังหวัด (เลขที่) ผย. คส. บ.\n1 บ้านพัก 2 ชั้น ต.ไชยวัฒนา อ.บัว จ.น่าน 13654 29/1/2547 ชื่อ 1,500,000.00\n2 บ้านพัก 2 ชั้น ต.ไชยวัฒนา อ.มัว จ.น่าน 13654 14/10/2556 ชื่อ 300,000.00\n3 บ้านพักชันเดียว จ.น่าน ต.พญาแก้ว อ.เชียงกลาง 11281 6/3/2543 ชื่อ 200,000.00\n4 บ้านพักชันเดียว ต.บ่อ อ.เมือง จ.น่าน นส 3 ข เล่ม 47 หน้า 169 เลขที่ 96 9/7/2544 ชื่อ 200,000.00\n5 ห้องชุด เขตดุสิต กทม. 75187 6/3/2561 ให้ 400,000.00\nหมายเหตุ ผย. = ผู้ยื่นบัญชี , คส. = คู่สมรส , บ. = บุตรที่ยังไม่บรรลุนิติภาวะ\nลงชื่อ ผู้ยื่นบัญชี\n- ลับ -",
  "lines": [
    {
      "text": "- ลับ -",
      "y": 0.773,
      "x": 4.068
    },
    {
      "text": "หน้า 14",
      "y": 1.137,
      "x": 6.887
    },
    {
      "text": "รายละเอียดประกอบรายการโรงเรือนและสิ่งปลูกสร้าง",
      "y": 1.326,
      "x": 4.053
    },
    {
      "text": "2,600,000.00",
      "y": 1.626,
      "x": 4.782
    },
    {
      "text": "5",
      "y": 1.628,
      "x": 2.779
    },
    {
      "text": "ผู้ยื่นบัญชี จำนวน.",
      "y": 1.646,
      "x": 2.127
    },
    {
      "text": "หลัง จำนวนเงินรวม",
      "y": 1.646,
      "x": 3.609
    },
    {
      "text": "บาท (ยกไปกรอกในบัญชีฯ หน้า 7)",
      "y": 1.669,
      "x": 6.094
    },
    {
      "text": "-",
      "y": 1.868,
      "x": 2.788
    },
    {
      "text": "หลัง จำนวนเงินรวม",
      "y": 1.886,
      "x": 3.607
    },
    {
      "text": "คู่สมรส จำนวน",
      "y": 1.896,
      "x": 2.165
    },
    {
      "text": "บาท (ยกไปกรอกในบัญชีฯ หน้า 7)",
      "y": 1.903,
      "x": 6.096
    },
    {
      "text": "บุตรที่ยังไม่บรรลุนิติภาวะ จำนวน \"",
      "y": 2.122,
      "x": 1.891
    },
    {
      "text": "หลัง จำนวนเงินรวม",
      "y": 2.122,
      "x": 3.623
    },
    {
      "text": "บาท (ยกไปกรอกในบัญชีฯ หน้า 7)",
      "y": 2.144,
      "x": 6.096
    },
    {
      "text": "ประเภท /",
      "y": 2.539,
      "x": 1.454
    },
    {
      "text": "ปลูกสร้างบน",
      "y": 2.548,
      "x": 4.004
    },
    {
      "text": "ที่ตั้ง",
      "y": 2.563,
      "x": 3.041
    },
    {
      "text": "ของ",
      "y": 2.606,
      "x": 7.1
    },
    {
      "text": "ลำดับ",
      "y": 2.618,
      "x": 0.821
    },
    {
      "text": "ว/ด/ป",
      "y": 2.634,
      "x": 4.638
    },
    {
      "text": "มูลค่าปัจจุบัน",
      "y": 2.647,
      "x": 6.155
    },
    {
      "text": "เลขที่",
      "y": 2.704,
      "x": 2.165
    },
    {
      "text": "เอกสารสิทธิ์",
      "y": 2.71,
      "x": 4.008
    },
    {
      "text": "ลักษณะ",
      "y": 2.712,
      "x": 1.452
    },
    {
      "text": "การได้มา",
      "y": 2.718,
      "x": 5.241
    },
    {
      "text": "ที่",
      "y": 2.793,
      "x": 0.824
    },
    {
      "text": "ที่ได้มา",
      "y": 2.797,
      "x": 4.641
    },
    {
      "text": "(โดยประมาณ)",
      "y": 2.813,
      "x": 6.155
    },
    {
      "text": "(เลขที่)",
      "y": 2.887,
      "x": 4.0
    },
    {
      "text": "สิ่งปลูกสร้าง",
      "y": 2.889,
      "x": 1.459
    },
    {
      "text": "ตำบล/อำเภอ/จังหวัด",
      "y": 2.896,
      "x": 3.046
    },
    {
      "text": "ผย.",
      "y": 2.924,
      "x": 6.84
    },
    {
      "text": "บ.",
      "y": 2.926,
      "x": 7.409
    },
    {
      "text": "คส.",
      "y": 2.93,
      "x": 7.132
    },
    {
      "text": "1",
      "y": 3.149,
      "x": 0.857
    },
    {
      "text": "ต.ไชยวัฒนา อ.บัว จ.น่าน",
      "y": 3.162,
      "x": 3.02
    },
    {
      "text": "บ้านพัก 2 ชั้น",
      "y": 3.167,
      "x": 1.424
    },
    {
      "text": "13654",
      "y": 3.171,
      "x": 3.98
    },
    {
      "text": "29/1/2547",
      "y": 3.181,
      "x": 4.631
    },
    {
      "text": "ชื่อ",
      "y": 3.185,
      "x": 5.207
    },
    {
      "text": "1,500,000.00",
      "y": 3.19,
      "x": 6.147
    },
    {
      "text": "บ้านพัก 2 ชั้น",
      "y": 3.397,
      "x": 1.418
    },
    {
      "text": "14/10/2556",
      "y": 3.406,
      "x": 4.64
    },
    {
      "text": "13654",
      "y": 3.408,
      "x": 3.987
    },
    {
      "text": "2",
      "y": 3.413,
      "x": 0.858
    },
    {
      "text": "ต.ไชยวัฒนา อ.มัว จ.น่าน",
      "y": 3.415,
      "x": 3.053
    },
    {
      "text": "ชื่อ",
      "y": 3.424,
      "x": 5.203
    },
    {
      "text": "300,000.00",
      "y": 3.436,
      "x": 6.157
    },
    {
      "text": "ต.พญาแก้ว อ.เชียงกลาง",
      "y": 3.589,
      "x": 3.037
    },
    {
      "text": "3",
      "y": 3.632,
      "x": 0.845
    },
    {
      "text": "11281",
      "y": 3.644,
      "x": 3.972
    },
    {
      "text": "บ้านพักชันเดียว",
      "y": 3.648,
      "x": 1.459
    },
    {
      "text": "6/3/2543",
      "y": 3.662,
      "x": 4.617
    },
    {
      "text": "200,000.00",
      "y": 3.662,
      "x": 6.14
    },
    {
      "text": "ชื่อ",
      "y": 3.67,
      "x": 5.211
    },
    {
      "text": "จ.น่าน",
      "y": 3.704,
      "x": 2.646
    },
    {
      "text": "นส 3 ข เล่ม 47",
      "y": 3.831,
      "x": 3.939
    },
    {
      "text": "4",
      "y": 3.879,
      "x": 0.846
    },
    {
      "text": "200,000.00",
      "y": 3.896,
      "x": 6.137
    },
    {
      "text": "ต.บ่อ อ.เมือง จ.น่าน",
      "y": 3.901,
      "x": 2.997
    },
    {
      "text": "ชื่อ",
      "y": 3.903,
      "x": 5.211
    },
    {
      "text": "บ้านพักชันเดียว",
      "y": 3.905,
      "x": 1.453
    },
    {
      "text": "9/7/2544",
      "y": 3.906,
      "x": 4.617
    },
    {
      "text": "หน้า 169 เลขที่ 96",
      "y": 3.935,
      "x": 3.997
    },
    {
      "text": "เขตดุสิต กทม.",
      "y": 4.132,
      "x": 2.977
    },
    {
      "text": "ให้",
      "y": 4.133,
      "x": 5.227
    },
    {
      "text": "5",
      "y": 4.138,
      "x": 0.852
    },
    {
      "text": "400,000.00",
      "y": 4.141,
      "x": 6.129
    },
    {
      "text": "75187",
      "y": 4.149,
      "x": 3.99
    },
    {
      "text": "6/3/2561",
      "y": 4.149,
      "x": 4.632
    },
    {
      "text": "ห้องชุด",
      "y": 4.153,
      "x": 1.395
    },
    {
      "text": "หมายเหตุ ผย. = ผู้ยื่นบัญชี , คส. = คู่สมรส , บ. = บุตรที่ยังไม่บรรลุนิติภาวะ",
      "y": 9.696,
      "x": 5.906
    },
    {
      "text": "ลงชื่อ",
      "y": 10.63,
      "x": 4.001
    },
    {
      "text": "ผู้ยื่นบัญชี",
      "y": 10.658,
      "x": 6.877
    },
    {
      "text": "- ลับ -",
      "y": 10.876,
      "x": 4.046
    }
  ]
}