{
  "doc_name": "วิทยา_ทรงคำ_สมาชิกสภาผู้แทนราษฎร_(ส.ส.)_กรณีพ้นจากตำแหน่ง_16_มิ.ย._2566.json",
  "page_number": 23,
  "page_index": 22,
  "total_pages": 37,
  "page_type": "buildings",
  "is_continuation": false,
  "is_extra_page": false,
  "matched_template_page": null,
  "content": "หน้า 14\nรายละเอียดประกอบรายการโรงเรือนและสิ่งปลูกสร้าง\nผู้ยื่นบัญชี จำนวน โรคม หลัง จำนวนเงินรวม 750,000 บาท (ยกไปกรอกในบัญชีฯ หน้า 7)\nคู่สมรส จำนวน 141 หลัง จำนวนเงินรวม 1350,000 บาท (ยกไปกรอกในบัญชีฯ หน้า 7)\nบุตรที่ยังไม่บรรลุนิติภาวะ จำนวน หลัง จำนวนเงินรวม บาท (ยกไปกรอกในบัญชีฯ หน้า 7)\nลำดับ ประเภท / ที่ตั้ง ปลูกสร้างบน ว/ด/ป มูลค่าปัจจุบัน ของ\nที่ ลักษณะ เลขที่ เอกสารสิทธิ์ ที่ได้มา การได้มา (โดยประมาณ)\nสิ่งปลูกสร้าง ตำบล/อำเภอ/จังหวัด (เลขที่) พ.ย. คส. ) บ.\n1 บ้านอาศัย 1,500, 000.00\nอ. สันทราย\nจ. เชียงใหม่ 2680\n60\n2 บันอาศัย 100,000.00\nอ.เมือง / 1. 36\nจ. เขือ us\nหมาย (หยด เอกสารอีซีเทสปลาแหนน์ 25 พ.ศ. 12\nหมายเหตุ ผย. = ผู้ยื่นบัญชี , คส. = คู่สมรส , บ. = บุตรที่ยังไม่บรรลุนิติภาวะ\nลงชื่อ ผู้ยื่นบัญชี\n- ลับ -",
  "lines": [
    {
      "text": "หน้า 14",
      "y": 0.574,
      "x": 6.909
    },
    {
      "text": "รายละเอียดประกอบรายการโรงเรือนและสิ่งปลูกสร้าง",
      "y": 0.784,
      "x": 3.926
    },
    {
      "text": "750,000",
      "y": 1.071,
      "x": 4.675
    },
    {
      "text": "ผู้ยื่นบัญชี จำนวน โรคม หลัง จำนวนเงินรวม",
      "y": 1.127,
      "x": 2.711
    },
    {
      "text": "บาท (ยกไปกรอกในบัญชีฯ หน้า 7)",
      "y": 1.143,
      "x": 6.076
    },
    {
      "text": "1350,000",
      "y": 1.343,
      "x": 4.647
    },
    {
      "text": "คู่สมรส จำนวน 141 หลัง จำนวนเงินรวม",
      "y": 1.392,
      "x": 2.759
    },
    {
      "text": "บาท (ยกไปกรอกในบัญชีฯ หน้า 7)",
      "y": 1.398,
      "x": 6.079
    },
    {
      "text": "หลัง จำนวนเงินรวม",
      "y": 1.637,
      "x": 3.467
    },
    {
      "text": "บุตรที่ยังไม่บรรลุนิติภาวะ จำนวน",
      "y": 1.639,
      "x": 1.523
    },
    {
      "text": "บาท (ยกไปกรอกในบัญชีฯ หน้า 7)",
      "y": 1.652,
      "x": 6.081
    },
    {
      "text": "ประเภท /",
      "y": 2.095,
      "x": 1.199
    },
    {
      "text": "ปลูกสร้างบน",
      "y": 2.1,
      "x": 3.873
    },
    {
      "text": "ที่ตั้ง",
      "y": 2.11,
      "x": 2.858
    },
    {
      "text": "ของ",
      "y": 2.151,
      "x": 7.126
    },
    {
      "text": "ลำดับ",
      "y": 2.179,
      "x": 0.529
    },
    {
      "text": "ว/ด/ป",
      "y": 2.186,
      "x": 4.542
    },
    {
      "text": "มูลค่าปัจจุบัน",
      "y": 2.194,
      "x": 6.124
    },
    {
      "text": "เลขที่",
      "y": 2.257,
      "x": 1.92
    },
    {
      "text": "เอกสารสิทธิ์",
      "y": 2.269,
      "x": 3.877
    },
    {
      "text": "ลักษณะ",
      "y": 2.274,
      "x": 1.199
    },
    {
      "text": "การได้มา",
      "y": 2.278,
      "x": 5.169
    },
    {
      "text": "ที่",
      "y": 2.355,
      "x": 0.538
    },
    {
      "text": "ที่ได้มา",
      "y": 2.36,
      "x": 4.544
    },
    {
      "text": "(โดยประมาณ)",
      "y": 2.375,
      "x": 6.137
    },
    {
      "text": "(เลขที่)",
      "y": 2.46,
      "x": 3.876
    },
    {
      "text": "สิ่งปลูกสร้าง",
      "y": 2.464,
      "x": 1.2
    },
    {
      "text": "ตำบล/อำเภอ/จังหวัด",
      "y": 2.469,
      "x": 2.865
    },
    {
      "text": "พ.ย.",
      "y": 2.491,
      "x": 6.872
    },
    {
      "text": "คส. )",
      "y": 2.495,
      "x": 7.213
    },
    {
      "text": "บ.",
      "y": 2.495,
      "x": 7.453
    },
    {
      "text": "บ้านอาศัย",
      "y": 2.768,
      "x": 1.108
    },
    {
      "text": "1,500, 000.00",
      "y": 2.782,
      "x": 6.165
    },
    {
      "text": "1",
      "y": 2.783,
      "x": 0.503
    },
    {
      "text": "อ. สันทราย",
      "y": 3.025,
      "x": 2.698
    },
    {
      "text": "จ. เชียงใหม่",
      "y": 3.27,
      "x": 2.721
    },
    {
      "text": "2680",
      "y": 3.309,
      "x": 4.478
    },
    {
      "text": "60",
      "y": 3.571,
      "x": 4.489
    },
    {
      "text": "บันอาศัย",
      "y": 3.794,
      "x": 1.114
    },
    {
      "text": "2",
      "y": 3.803,
      "x": 0.472
    },
    {
      "text": "100,000.00",
      "y": 3.827,
      "x": 6.175
    },
    {
      "text": "อ.เมือง /",
      "y": 4.066,
      "x": 2.68
    },
    {
      "text": "36",
      "y": 4.077,
      "x": 4.494
    },
    {
      "text": "1.",
      "y": 4.215,
      "x": 3.576
    },
    {
      "text": "จ. เขือ us",
      "y": 4.305,
      "x": 2.702
    },
    {
      "text": "เอกสารอีซีเทสปลาแหนน์",
      "y": 5.355,
      "x": 3.711
    },
    {
      "text": "25 พ.ศ. 12",
      "y": 5.365,
      "x": 6.192
    },
    {
      "text": "หมาย (หยด",
      "y": 5.378,
      "x": 1.184
    },
    {
      "text": "หมายเหตุ ผย. = ผู้ยื่นบัญชี , คส. = คู่สมรส , บ. = บุตรที่ยังไม่บรรลุนิติภาวะ",
      "y": 9.781,
      "x": 5.896
    },
    {
      "text": "ลงชื่อ",
      "y": 10.791,
      "x": 3.921
    },
    {
      "text": "ผู้ยื่นบัญชี",
      "y": 10.811,
      "x": 6.934
    },
    {
      "text": "- ลับ -",
      "y": 11.049,
      "x": 3.966
    }
  ]
}