{
  "doc_name": "ภูดิท_อินสุวรรณ์_สมาชิกสภาผู้แทนราษฎร_(ส.ส.)_กรณีพ้นจากตำแหน่ง_5_เม.ย._2566.json",
  "page_number": 15,
  "page_index": 14,
  "total_pages": 37,
  "page_type": "deposits",
  "is_continuation": false,
  "is_extra_page": false,
  "matched_template_page": null,
  "content": "- ลับ -\nหน้า 10\nรายละเอียดประกอบรายการเงินฝาก\nผู้ยื่นบัญชี จำนวน 1 บัญชี จำนวนเงินรวม 724.61 บาท (ยกไปกรอกในบัญชีฯ หน้า 7)\nคู่สมรส จำนวน 1 บัญชี จำนวนเงินรวม 364,003. 45. บาท (ยกไปกรอกในบัญชีฯ หน้า 7)\nบุตรที่ยังไม่บรรลุนิติภาวะ จำนวน บัญชี จำนวนเงินรวม บาท (ยกไปกรอกในบัญชีฯ หน้า 7)\nลำดับ สถาบันการเงิน / สาขา เลขที่บัญชี จำนวนเงิน ของ\nที่. ผย. คส. บ.\n1 ธนาคารกรุงไทย สาขารัฐสภา 724.61\n1. ณาคารกสิกรไทย สาขาทับคล้อ 364,003.45\nหมายเหตุ ผย. = ผู้ยื่นบัญชี , คส. = คู่สมรส , บ. = บุตรที่ยังไม่บรรลุนิติภาวะ\nลงชื่อ ๖ ผู้ยื่นบัญชี\n- ลับ -",
  "lines": [
    {
      "text": "- ลับ -",
      "y": 0.683,
      "x": 4.214
    },
    {
      "text": "หน้า 10",
      "y": 1.041,
      "x": 7.088
    },
    {
      "text": "รายละเอียดประกอบรายการเงินฝาก",
      "y": 1.247,
      "x": 4.193
    },
    {
      "text": "1",
      "y": 1.528,
      "x": 2.928
    },
    {
      "text": "724.61",
      "y": 1.533,
      "x": 4.886
    },
    {
      "text": "ผู้ยื่นบัญชี จำนวน",
      "y": 1.577,
      "x": 2.245
    },
    {
      "text": "บัญชี จำนวนเงินรวม",
      "y": 1.589,
      "x": 3.749
    },
    {
      "text": "บาท (ยกไปกรอกในบัญชีฯ หน้า 7)",
      "y": 1.591,
      "x": 6.287
    },
    {
      "text": "364,003. 45.",
      "y": 1.784,
      "x": 4.939
    },
    {
      "text": "1",
      "y": 1.796,
      "x": 2.959
    },
    {
      "text": "บัญชี จำนวนเงินรวม",
      "y": 1.827,
      "x": 3.746
    },
    {
      "text": "บาท (ยกไปกรอกในบัญชีฯ หน้า 7)",
      "y": 1.832,
      "x": 6.294
    },
    {
      "text": "คู่สมรส จำนวน",
      "y": 1.844,
      "x": 2.294
    },
    {
      "text": "บัญชี จำนวนเงินรวม",
      "y": 2.073,
      "x": 3.733
    },
    {
      "text": "บาท (ยกไปกรอกในบัญชีฯ หน้า 7)",
      "y": 2.077,
      "x": 6.279
    },
    {
      "text": "บุตรที่ยังไม่บรรลุนิติภาวะ จำนวน",
      "y": 2.079,
      "x": 1.845
    },
    {
      "text": "ลำดับ",
      "y": 2.498,
      "x": 0.89
    },
    {
      "text": "ของ",
      "y": 2.506,
      "x": 7.428
    },
    {
      "text": "เลขที่บัญชี",
      "y": 2.575,
      "x": 4.765
    },
    {
      "text": "จำนวนเงิน",
      "y": 2.576,
      "x": 6.308
    },
    {
      "text": "สถาบันการเงิน / สาขา",
      "y": 2.587,
      "x": 2.48
    },
    {
      "text": "ที่.",
      "y": 2.669,
      "x": 0.906
    },
    {
      "text": "ผย.",
      "y": 2.737,
      "x": 7.119
    },
    {
      "text": "คส.",
      "y": 2.74,
      "x": 7.425
    },
    {
      "text": "บ.",
      "y": 2.74,
      "x": 7.73
    },
    {
      "text": "724.61",
      "y": 2.944,
      "x": 6.584
    },
    {
      "text": "ธนาคารกรุงไทย สาขารัฐสภา",
      "y": 2.953,
      "x": 2.015
    },
    {
      "text": "1",
      "y": 2.96,
      "x": 0.897
    },
    {
      "text": "364,003.45",
      "y": 3.19,
      "x": 6.601
    },
    {
      "text": "ณาคารกสิกรไทย สาขาทับคล้อ",
      "y": 3.204,
      "x": 2.06
    },
    {
      "text": "1.",
      "y": 3.221,
      "x": 0.886
    },
    {
      "text": "หมายเหตุ ผย. = ผู้ยื่นบัญชี , คส. = คู่สมรส , บ. = บุตรที่ยังไม่บรรลุนิติภาวะ",
      "y": 9.834,
      "x": 6.109
    },
    {
      "text": "๖",
      "y": 10.559,
      "x": 5.556
    },
    {
      "text": "ลงชื่อ",
      "y": 10.702,
      "x": 4.162
    },
    {
      "text": "ผู้ยื่นบัญชี",
      "y": 10.702,
      "x": 7.118
    },
    {
      "text": "- ลับ -",
      "y": 10.99,
      "x": 4.211
    }
  ]
}