{
  "doc_name": "องอาจ_คล้ามไพบูลย์_สมาชิกสภาผู้แทนราษฎร_(ส.ส.)_กรณีพ้นจากตำแหน่ง_16_มิ.ย._2566.json",
  "page_number": 36,
  "page_index": 35,
  "total_pages": 37,
  "page_type": "documents_list",
  "is_continuation": false,
  "is_extra_page": false,
  "matched_template_page": null,
  "content": "- ลับ -\nรายละเอียดของเอกสารประกอบ\nลำดับที่ รายการเอกสาร จำนวน\n(แผ่น)\n1 สำเนาแบบแสดงรายการภาษีเงินได้บุคคลธรรมดาในรอบปีภาษีที่ผ่านมา (ภ.ง.ด. 90, 91) 15\n2 เอกสารประกอบประเภทรายการทรัพย์สิน\n(1) เงินสด\n(2) เงินฝาก 22\n(3) เงินลงทุน 18\n(4) เงินให้กู้ยืม\n(5) ที่ดิน 19\n(6) โรงเรือนและสิ่งปลูกสร้าง\n(7) ยานพาหนะ 3\n(8) สิทธิและสัมปทาน\n(9) ทรัพย์สินอื่น 9\n3 เอกสารประกอบประเภทรายการหนี้สิน\n(1) เงินเบิกเกินบัญชี\n(2) เงินกู้จากธนาคารและสถาบันการเงินอื่น\n(3) หนี้สินที่มีหลักฐานเป็นหนังสือ\n(4) หนี้สินอื่น\n4 สำเนาเอกสารอื่น ๆ (อาทิ หนังสือหรือคำสั่งแต่งตั้ง หนังสือลาออก บัตรประจำตัวประชาชน -\nใบสำคัญจดทะเบียนสมรส ใบสำคัญการหย่า หนังสือสำคัญแสดงการเปลี่ยนชื่อตัว มรณบัตร เป็นต้น)\nรวมเอกสารทั้งสิ้น 87\nหมายเหตุ สำเนาเอกสารอื่นๆคือรายละเอียดประกอบรายการ\nเงินลงทุน\nสอบถามข้อมูลเพิ่มเติม ได้ที่\nสายด่วน ป.ป.ช. ลงชื่อ ผู้ยื่นบัญชี\nwww.nacc.go.th 1 2 05\n- ลับ -",
  "lines": [
    {
      "text": "- ลับ -",
      "y": 0.168,
      "x": 4.101
    },
    {
      "text": "รายละเอียดของเอกสารประกอบ",
      "y": 0.83,
      "x": 4.079
    },
    {
      "text": "จำนวน",
      "y": 1.309,
      "x": 7.37
    },
    {
      "text": "ลำดับที่",
      "y": 1.403,
      "x": 0.896
    },
    {
      "text": "รายการเอกสาร",
      "y": 1.431,
      "x": 4.096
    },
    {
      "text": "(แผ่น)",
      "y": 1.534,
      "x": 7.365
    },
    {
      "text": "15",
      "y": 1.817,
      "x": 7.358
    },
    {
      "text": "สำเนาแบบแสดงรายการภาษีเงินได้บุคคลธรรมดาในรอบปีภาษีที่ผ่านมา (ภ.ง.ด. 90, 91)",
      "y": 1.83,
      "x": 3.49
    },
    {
      "text": "1",
      "y": 1.84,
      "x": 0.91
    },
    {
      "text": "เอกสารประกอบประเภทรายการทรัพย์สิน",
      "y": 2.142,
      "x": 4.481
    },
    {
      "text": "2",
      "y": 2.148,
      "x": 0.909
    },
    {
      "text": "(1) เงินสด",
      "y": 2.443,
      "x": 1.553
    },
    {
      "text": "(2) เงินฝาก",
      "y": 2.737,
      "x": 1.584
    },
    {
      "text": "22",
      "y": 2.755,
      "x": 7.373
    },
    {
      "text": "(3) เงินลงทุน",
      "y": 3.047,
      "x": 1.624
    },
    {
      "text": "18",
      "y": 3.066,
      "x": 7.37
    },
    {
      "text": "(4) เงินให้กู้ยืม",
      "y": 3.337,
      "x": 1.65
    },
    {
      "text": "(5) ที่ดิน",
      "y": 3.605,
      "x": 1.51
    },
    {
      "text": "19",
      "y": 3.638,
      "x": 7.395
    },
    {
      "text": "(6) โรงเรือนและสิ่งปลูกสร้าง",
      "y": 3.915,
      "x": 2.02
    },
    {
      "text": "(7) ยานพาหนะ",
      "y": 4.223,
      "x": 1.683
    },
    {
      "text": "3",
      "y": 4.232,
      "x": 7.448
    },
    {
      "text": "(8) สิทธิและสัมปทาน",
      "y": 4.519,
      "x": 1.843
    },
    {
      "text": "(9) ทรัพย์สินอื่น",
      "y": 4.798,
      "x": 1.697
    },
    {
      "text": "9",
      "y": 4.821,
      "x": 7.428
    },
    {
      "text": "เอกสารประกอบประเภทรายการหนี้สิน",
      "y": 5.096,
      "x": 4.485
    },
    {
      "text": "3",
      "y": 5.111,
      "x": 0.907
    },
    {
      "text": "(1) เงินเบิกเกินบัญชี",
      "y": 5.406,
      "x": 1.799
    },
    {
      "text": "(2) เงินกู้จากธนาคารและสถาบันการเงินอื่น",
      "y": 5.694,
      "x": 2.378
    },
    {
      "text": "(3) หนี้สินที่มีหลักฐานเป็นหนังสือ",
      "y": 5.986,
      "x": 2.137
    },
    {
      "text": "(4) หนี้สินอื่น",
      "y": 6.274,
      "x": 1.631
    },
    {
      "text": "สำเนาเอกสารอื่น ๆ (อาทิ หนังสือหรือคำสั่งแต่งตั้ง หนังสือลาออก บัตรประจำตัวประชาชน",
      "y": 6.544,
      "x": 3.571
    },
    {
      "text": "4",
      "y": 6.554,
      "x": 0.915
    },
    {
      "text": "-",
      "y": 6.661,
      "x": 7.405
    },
    {
      "text": "ใบสำคัญจดทะเบียนสมรส ใบสำคัญการหย่า หนังสือสำคัญแสดงการเปลี่ยนชื่อตัว มรณบัตร เป็นต้น)",
      "y": 6.772,
      "x": 3.797
    },
    {
      "text": "รวมเอกสารทั้งสิ้น",
      "y": 7.098,
      "x": 6.435
    },
    {
      "text": "87",
      "y": 7.116,
      "x": 7.341
    },
    {
      "text": "สำเนาเอกสารอื่นๆคือรายละเอียดประกอบรายการ",
      "y": 7.574,
      "x": 4.223
    },
    {
      "text": "หมายเหตุ",
      "y": 7.702,
      "x": 0.853
    },
    {
      "text": "เงินลงทุน",
      "y": 7.862,
      "x": 1.813
    },
    {
      "text": "สอบถามข้อมูลเพิ่มเติม ได้ที่",
      "y": 10.182,
      "x": 2.055
    },
    {
      "text": "สายด่วน ป.ป.ช.",
      "y": 10.484,
      "x": 2.336
    },
    {
      "text": "ลงชื่อ",
      "y": 10.549,
      "x": 4.053
    },
    {
      "text": "ผู้ยื่นบัญชี",
      "y": 10.563,
      "x": 7.107
    },
    {
      "text": "1 2 05",
      "y": 10.648,
      "x": 2.332
    },
    {
      "text": "www.nacc.go.th",
      "y": 10.792,
      "x": 2.254
    },
    {
      "text": "- ลับ -",
      "y": 10.937,
      "x": 4.095
    }
  ]
}