{
  "doc_name": "ชาดา_ไทยเศรษฐ์_สมาชิกสภาผู้แทนราษฎร_(ส.ส.)_กรณีพ้นจากตำแหน่ง_17_ก.ค._2566.json",
  "page_number": 8,
  "page_index": 7,
  "total_pages": 31,
  "page_type": "unknown",
  "is_continuation": false,
  "is_extra_page": false,
  "matched_template_page": null,
  "content": "1\nลำดับที่ ชื่อ - ชื่อสกุล อายุ ที่อยู่ และสถานศึกษา / ที่ทำงาน\n6 เด็กหญิงปรินดา ไทยเศรษฐ์ 13 ปี ที่อยู่ .... ถ.มณีรัตน์ ต.อุทัยใหม่ อ.เมือง.\nJ .จ.อุทัยธานี .. 61000 ...\n...\nวัน เดือน ปี เกิด สถานศึกษา ... โรงเรียนมารีย์วิทย์ .. อ.บางละมุง\nที่ทำงาน ...................\n1 . 7 เด็กหญิงพิมพ์ลักษณ์ เทียนทอง 10 ปี ที่อยู่ .... ซ.วิภาวดีรังสิต 16/27 แขวง ...\n.รัชดาภิเษก เขตดินแดง กรุงเทพมหานคร ...\nวัน เดือน ปี เกิด ! สถานศึกษา ....................\nที่ทำงาน .. ......\n1.00.00\n10\nสำเนาถูกต้อง\nmedã\n(นายชาดา ไทยเศรษฐ์)\n-\n-",
  "lines": [
    {
      "text": "1",
      "y": 0.274,
      "x": 0.126
    },
    {
      "text": "ลำดับที่",
      "y": 1.025,
      "x": 0.912
    },
    {
      "text": "ชื่อ - ชื่อสกุล",
      "y": 1.039,
      "x": 2.42
    },
    {
      "text": "ที่อยู่ และสถานศึกษา / ที่ทำงาน",
      "y": 1.057,
      "x": 5.694
    },
    {
      "text": "อายุ",
      "y": 1.07,
      "x": 3.942
    },
    {
      "text": "เด็กหญิงปรินดา ไทยเศรษฐ์",
      "y": 1.317,
      "x": 2.424
    },
    {
      "text": "6",
      "y": 1.33,
      "x": 0.898
    },
    {
      "text": "13 ปี",
      "y": 1.332,
      "x": 3.945
    },
    {
      "text": "ที่อยู่ .... ถ.มณีรัตน์ ต.อุทัยใหม่ อ.เมือง.",
      "y": 1.335,
      "x": 5.308
    },
    {
      "text": "J",
      "y": 1.477,
      "x": 0.103
    },
    {
      "text": ".จ.อุทัยธานี .. 61000 ...",
      "y": 1.627,
      "x": 4.985
    },
    {
      "text": "...",
      "y": 1.651,
      "x": 4.26
    },
    {
      "text": "วัน เดือน ปี เกิด",
      "y": 1.878,
      "x": 1.64
    },
    {
      "text": "สถานศึกษา ... โรงเรียนมารีย์วิทย์ .. อ.บางละมุง",
      "y": 1.917,
      "x": 5.499
    },
    {
      "text": "ที่ทำงาน ...................",
      "y": 2.174,
      "x": 4.777
    },
    {
      "text": "เด็กหญิงพิมพ์ลักษณ์ เทียนทอง",
      "y": 2.45,
      "x": 2.4
    },
    {
      "text": "10 ปี",
      "y": 2.46,
      "x": 3.938
    },
    {
      "text": ". 7",
      "y": 2.464,
      "x": 0.876
    },
    {
      "text": "ที่อยู่ .... ซ.วิภาวดีรังสิต 16/27 แขวง ...",
      "y": 2.472,
      "x": 5.299
    },
    {
      "text": "1",
      "y": 2.497,
      "x": 0.096
    },
    {
      "text": ".รัชดาภิเษก เขตดินแดง กรุงเทพมหานคร ...",
      "y": 2.762,
      "x": 5.464
    },
    {
      "text": "วัน เดือน ปี เกิด !",
      "y": 3.012,
      "x": 1.711
    },
    {
      "text": "สถานศึกษา ....................",
      "y": 3.025,
      "x": 4.909
    },
    {
      "text": "ที่ทำงาน ..",
      "y": 3.297,
      "x": 4.475
    },
    {
      "text": "......",
      "y": 3.328,
      "x": 4.966
    },
    {
      "text": "1.00.00",
      "y": 6.096,
      "x": 4.239
    },
    {
      "text": "10",
      "y": 7.569,
      "x": 0.194
    },
    {
      "text": "สำเนาถูกต้อง",
      "y": 7.73,
      "x": 5.836
    },
    {
      "text": "medã",
      "y": 8.089,
      "x": 6.288
    },
    {
      "text": "(นายชาดา ไทยเศรษฐ์)",
      "y": 8.489,
      "x": 5.827
    },
    {
      "text": "-",
      "y": 11.116,
      "x": 0.071
    },
    {
      "text": "-",
      "y": 11.499,
      "x": 0.085
    }
  ]
}