{
  "doc_name": "ไพลิน_เทียนสุวรรณ_สมาชิกสภาผู้แทนราษฎร_(ส.ส.)_กรณีพ้นจากตำแหน่ง_15_พ.ค._2566.json",
  "page_number": 6,
  "page_index": 5,
  "total_pages": 24,
  "page_type": "siblings",
  "is_continuation": false,
  "is_extra_page": false,
  "matched_template_page": null,
  "content": "- ลับ -\nหน้า 4\nพี่น้อง พี่น้องร่วมบิดามารดา หรือร่วมบิดา หรือมารดา จำนวน 2 คน\nลำดับที่ ชื่อ-ชื่อสกุล อายุ ที่อยู่ และ ที่ทำงาน\n1 ที่อยู่ .......... -\nนายสิริศักดิ์ เทียนสุวรรณ (ตาย)\nที่ทำงาน\nที่อยู่. ซอยอุ่นอารี ตำบลท้ายบ้านใหม่\n2 นายวีระศักดิ์ เทียนสุวรรณ 43 ปี อำเภอเมืองสมุทรปราการ จังหวัดสมุทรปราการ\nที่ทำงาน ..\nที่อยู่\n3\nที่ทำงาน\nA.0.000 ที่อยู่\n4\nที่ทำงาน ....\n:\nที่อยู่:\n5\nที่ทำงาน .. ...\nหมายเหตุ กรณีมีพี่น้องมากกว่าช่องรายการ ผู้ยื่นบัญชีสามารถจัดทำข้อมูลพี่น้องเป็นใบแทรกให้ครบทุกคนได้\n\"ในสวน เทียนสุวรรณ ผู้ยื่นบัญชี\nลงชื่อ\n(นางสาวไพลิน เทียนสุวรรณ)\n- ลับ -",
  "lines": [
    {
      "text": "- ลับ -",
      "y": 0.261,
      "x": 4.189
    },
    {
      "text": "หน้า 4",
      "y": 0.612,
      "x": 7.166
    },
    {
      "text": "พี่น้อง",
      "y": 1.039,
      "x": 1.237
    },
    {
      "text": "พี่น้องร่วมบิดามารดา หรือร่วมบิดา หรือมารดา จำนวน 2 คน",
      "y": 1.047,
      "x": 3.614
    },
    {
      "text": "ที่อยู่ และ ที่ทำงาน",
      "y": 1.606,
      "x": 6.239
    },
    {
      "text": "ชื่อ-ชื่อสกุล",
      "y": 1.643,
      "x": 2.74
    },
    {
      "text": "ลำดับที่",
      "y": 1.645,
      "x": 1.234
    },
    {
      "text": "อายุ",
      "y": 1.655,
      "x": 4.306
    },
    {
      "text": "-",
      "y": 2.098,
      "x": 6.023
    },
    {
      "text": "ที่อยู่ ..........",
      "y": 2.137,
      "x": 5.0
    },
    {
      "text": "1",
      "y": 2.172,
      "x": 1.236
    },
    {
      "text": "นายสิริศักดิ์ เทียนสุวรรณ (ตาย)",
      "y": 2.412,
      "x": 2.76
    },
    {
      "text": "ที่ทำงาน",
      "y": 2.633,
      "x": 4.943
    },
    {
      "text": "ซอยอุ่นอารี ตำบลท้ายบ้านใหม่",
      "y": 3.408,
      "x": 6.412
    },
    {
      "text": "ที่อยู่.",
      "y": 3.446,
      "x": 4.887
    },
    {
      "text": "อำเภอเมืองสมุทรปราการ จังหวัดสมุทรปราการ",
      "y": 3.66,
      "x": 6.318
    },
    {
      "text": "43 ปี",
      "y": 3.747,
      "x": 4.306
    },
    {
      "text": "2",
      "y": 3.756,
      "x": 1.251
    },
    {
      "text": "นายวีระศักดิ์ เทียนสุวรรณ",
      "y": 3.764,
      "x": 2.533
    },
    {
      "text": "ที่ทำงาน ..",
      "y": 3.949,
      "x": 4.975
    },
    {
      "text": "ที่อยู่",
      "y": 4.788,
      "x": 4.848
    },
    {
      "text": "3",
      "y": 5.091,
      "x": 1.253
    },
    {
      "text": "ที่ทำงาน",
      "y": 5.285,
      "x": 4.97
    },
    {
      "text": "A.0.000",
      "y": 6.1,
      "x": 4.246
    },
    {
      "text": "ที่อยู่",
      "y": 6.109,
      "x": 4.884
    },
    {
      "text": "4",
      "y": 6.412,
      "x": 1.274
    },
    {
      "text": "ที่ทำงาน ....",
      "y": 6.609,
      "x": 5.074
    },
    {
      "text": ":",
      "y": 7.05,
      "x": 4.016
    },
    {
      "text": "ที่อยู่:",
      "y": 7.444,
      "x": 4.895
    },
    {
      "text": "5",
      "y": 7.617,
      "x": 1.284
    },
    {
      "text": "ที่ทำงาน ..",
      "y": 7.919,
      "x": 5.004
    },
    {
      "text": "...",
      "y": 7.931,
      "x": 5.421
    },
    {
      "text": "หมายเหตุ กรณีมีพี่น้องมากกว่าช่องรายการ ผู้ยื่นบัญชีสามารถจัดทำข้อมูลพี่น้องเป็นใบแทรกให้ครบทุกคนได้",
      "y": 9.065,
      "x": 3.813
    },
    {
      "text": "\"ในสวน เทียนสุวรรณ",
      "y": 9.886,
      "x": 5.396
    },
    {
      "text": "ผู้ยื่นบัญชี",
      "y": 10.022,
      "x": 7.061
    },
    {
      "text": "ลงชื่อ",
      "y": 10.036,
      "x": 4.188
    },
    {
      "text": "(นางสาวไพลิน เทียนสุวรรณ)",
      "y": 10.229,
      "x": 5.669
    },
    {
      "text": "- ลับ -",
      "y": 10.981,
      "x": 4.236
    }
  ]
}