{
  "doc_name": "ยอดยิ่ง_แสนยากุล_สมาชิกสภาผู้แทนราษฎร_(ส.ส.)_กรณีพ้นจากตำแหน่ง_12_มิ.ย._2566.json",
  "page_number": 16,
  "page_index": 15,
  "total_pages": 37,
  "page_type": "unknown",
  "is_continuation": false,
  "is_extra_page": false,
  "matched_template_page": null,
  "content": "- ลับ -\nคำอธิบายรายการเงินลงทุน ตัวอย่างเอกสารประกอบ\nเงินลงทุน หมายถึง เงินลงทุนในหลักทรัพย์รัฐบาลและที่รัฐบาล - สำเนาพันธบัตร\nค้ำประกัน หลักทรัพย์จดทะเบียนและรับอนุญาต หลักทรัพย์และ - สำเนาหลักทรัพย์\nเงินลงทุนอื่น - สำเนาใบสำคัญแสดงสิทธิ (Warrant) ที่จะซื้อหุ้นกู้/\n- หลักทรัพย์รัฐบาลและที่รัฐบาลค้ำประกัน หมายถึง หลักทรัพย์ที่ หน่วยลงทุน\nรัฐบาลหรือหน่วยงานของรัฐออกให้ เช่น พันธบัตรรัฐบาล พันธบัตร -สำเนาหนังสือรับรองของบริษัทหลักทรัพย์หรือนายทะเบียน\nธนาคารอาคารสงเคราะห์ พันธบัตรออมทรัพย์ช่วยชาติ เป็นต้น หลักทรัพย์ (Broker) หรือศูนย์รับฝากหลักทรัพย์ ณ .วันที่มี\nหน้าที่แสดงรายการทรัพย์สินและหนี้สิน\n- หลักทรัพย์จดทะเบียนและรับอนุญาต หมายถึง หลักทรัพย์ของ - สำเนาหลักทรัพย์หรือสำเนาหนังสือรับรองของบริษัท หรือ\nบริษัทที่จดทะเบียนและได้รับอนุญาตให้ทำการ ซื้อ - ขาย ในตลาด สำเนาบัญชีรายชื่อผู้ถือหุ้น (แบบ บอจ.5) ”\nหลักทรัพย์แห่งประเทศไทย เช่น หุ้นสามัญ. หุ้นบุริมสิทธิ หุ้นกู้ - สำเนาหนังสือรับรองของห้างหุ้นส่วนหรือหลักฐานการ\nหน่วยลงทุน สิทธิที่จะซื้อหุ้น/หุ้นกู้/หน่วยลงทุนหรือตราสารอื่นใด เป็นหุ้นส่วน\nที่คณะกรรมการกำกับหลักทรัพย์และตลาดหลักทรัพย์กำหนด - สำเนาหลักฐานแสดงการเป็นผู้รับประโยชน์ในทรัสต์\nกองทุนรวม กองทรัสต์ เป็นต้น - กรณีหุ้นในสหกรณ์ออมทรัพย์ ให้ใช้หนังสือรับรองจากสหกรณ์\nออมทรัพย์ ณ วันที่มีหน้าที่แสดงรายการทรัพย์สินและหนี้สิน\n- หลักทรัพย์และเงินลงทุนอื่น หมายถึง หลักทรัพย์ของบริษัทที่มิได้ หรือสำเนาใบเสร็จรับเงินจากสหกรณ์ออมทรัพย์ที่ระบุ\nทำการซื้อขาย ในตลาดหลักทรัพย์แห่งประเทศไทย เงินลงทุน จำนวนหุ้น\nในห้างหุ้นส่วน หรือกิจการค้าอื่น ๆ ที่ดำเนินธุรกิจเป็นส่วนตัว กรณีเป็นกิจการค้าอื่นที่ดำเนินธุรกิจเป็นส่วนตัวให้ระบุสถานที่\nเช่น หุ้นบุริมสิทธิ หุ้นสามัญ หุ้นกู้ กิจการเลี้ยงสัตว์เพื่อการค้า ดำเนินกิจการ พร้อมทั้งภาพถ่ายสถานที่ดำเนินกิจการ สำเนา’\nการลงทุนทางการเกษตร กิจการร้านค้าขายของชำ เป็นต้น ทะเบียนพาณชย์ (ถ้ามี) และบัญชีรายการทรัพย์สิน(ถ้ามี)\n- กรณีเป็นกิจการเลี้ยงสัตว์เพื่อการค้า การลงทุนทางการเกษตร\nให้ระบุสถานที่ดำเนินกิจการ พร้อมทั้งภาพถ่ายสถานที่ดำเนิน\nกิจการ และบัญชีรายการทรัพย์สิน หรืออุปกรณ์เครื่องมือ\nทางการเกษตร เช่น เครื่องสีข้าว เครื่องเพาะกล้า เครื่อง\n: เกี่ยวนวดข้าว เป็นต้น\nหลักฐานอื่นใด ที่แสดงยอดเงินลงทุนคงเหลือ ณ วันที่มีหน้าที่\nแสดงรายการทรัพย์สินและหนี้สิน\nลับ",
  "lines": [
    {
      "text": "- ลับ -",
      "y": 0.662,
      "x": 4.051
    },
    {
      "text": "ตัวอย่างเอกสารประกอบ",
      "y": 1.789,
      "x": 5.654
    },
    {
      "text": "คำอธิบายรายการเงินลงทุน",
      "y": 1.802,
      "x": 2.359
    },
    {
      "text": "เงินลงทุน หมายถึง เงินลงทุนในหลักทรัพย์รัฐบาลและที่รัฐบาล",
      "y": 2.349,
      "x": 2.213
    },
    {
      "text": "- สำเนาพันธบัตร",
      "y": 2.349,
      "x": 4.537
    },
    {
      "text": "ค้ำประกัน หลักทรัพย์จดทะเบียนและรับอนุญาต หลักทรัพย์และ",
      "y": 2.566,
      "x": 2.221
    },
    {
      "text": "- สำเนาหลักทรัพย์",
      "y": 2.566,
      "x": 4.599
    },
    {
      "text": "- สำเนาใบสำคัญแสดงสิทธิ (Warrant) ที่จะซื้อหุ้นกู้/",
      "y": 2.766,
      "x": 5.39
    },
    {
      "text": "เงินลงทุนอื่น",
      "y": 2.776,
      "x": 0.978
    },
    {
      "text": "- หลักทรัพย์รัฐบาลและที่รัฐบาลค้ำประกัน หมายถึง หลักทรัพย์ที่",
      "y": 2.982,
      "x": 2.259
    },
    {
      "text": "หน่วยลงทุน",
      "y": 2.996,
      "x": 4.41
    },
    {
      "text": "-สำเนาหนังสือรับรองของบริษัทหลักทรัพย์หรือนายทะเบียน",
      "y": 3.189,
      "x": 5.546
    },
    {
      "text": "รัฐบาลหรือหน่วยงานของรัฐออกให้ เช่น พันธบัตรรัฐบาล พันธบัตร",
      "y": 3.204,
      "x": 2.265
    },
    {
      "text": "หลักทรัพย์ (Broker) หรือศูนย์รับฝากหลักทรัพย์ ณ .วันที่มี",
      "y": 3.403,
      "x": 5.505
    },
    {
      "text": "ธนาคารอาคารสงเคราะห์ พันธบัตรออมทรัพย์ช่วยชาติ เป็นต้น",
      "y": 3.415,
      "x": 2.175
    },
    {
      "text": "หน้าที่แสดงรายการทรัพย์สินและหนี้สิน",
      "y": 3.609,
      "x": 5.07
    },
    {
      "text": "- สำเนาหลักทรัพย์หรือสำเนาหนังสือรับรองของบริษัท หรือ",
      "y": 3.828,
      "x": 5.534
    },
    {
      "text": "- หลักทรัพย์จดทะเบียนและรับอนุญาต หมายถึง หลักทรัพย์ของ",
      "y": 3.838,
      "x": 2.226
    },
    {
      "text": "สำเนาบัญชีรายชื่อผู้ถือหุ้น (แบบ บอจ.5) ”",
      "y": 4.047,
      "x": 5.126
    },
    {
      "text": "บริษัทที่จดทะเบียนและได้รับอนุญาตให้ทำการ ซื้อ - ขาย ในตลาด",
      "y": 4.05,
      "x": 2.233
    },
    {
      "text": "- สำเนาหนังสือรับรองของห้างหุ้นส่วนหรือหลักฐานการ",
      "y": 4.26,
      "x": 5.434
    },
    {
      "text": "หลักทรัพย์แห่งประเทศไทย เช่น หุ้นสามัญ. หุ้นบุริมสิทธิ หุ้นกู้",
      "y": 4.265,
      "x": 2.132
    },
    {
      "text": "เป็นหุ้นส่วน",
      "y": 4.464,
      "x": 4.421
    },
    {
      "text": "หน่วยลงทุน สิทธิที่จะซื้อหุ้น/หุ้นกู้/หน่วยลงทุนหรือตราสารอื่นใด",
      "y": 4.477,
      "x": 2.165
    },
    {
      "text": "- สำเนาหลักฐานแสดงการเป็นผู้รับประโยชน์ในทรัสต์",
      "y": 4.673,
      "x": 5.372
    },
    {
      "text": "ที่คณะกรรมการกำกับหลักทรัพย์และตลาดหลักทรัพย์กำหนด",
      "y": 4.684,
      "x": 2.117
    },
    {
      "text": "- กรณีหุ้นในสหกรณ์ออมทรัพย์ ให้ใช้หนังสือรับรองจากสหกรณ์",
      "y": 4.878,
      "x": 5.632
    },
    {
      "text": "กองทุนรวม กองทรัสต์ เป็นต้น",
      "y": 4.906,
      "x": 1.387
    },
    {
      "text": "ออมทรัพย์ ณ วันที่มีหน้าที่แสดงรายการทรัพย์สินและหนี้สิน",
      "y": 5.092,
      "x": 5.541
    },
    {
      "text": "หรือสำเนาใบเสร็จรับเงินจากสหกรณ์ออมทรัพย์ที่ระบุ",
      "y": 5.304,
      "x": 5.386
    },
    {
      "text": "- หลักทรัพย์และเงินลงทุนอื่น หมายถึง หลักทรัพย์ของบริษัทที่มิได้",
      "y": 5.316,
      "x": 2.261
    },
    {
      "text": "ทำการซื้อขาย ในตลาดหลักทรัพย์แห่งประเทศไทย เงินลงทุน",
      "y": 5.524,
      "x": 2.146
    },
    {
      "text": "จำนวนหุ้น",
      "y": 5.526,
      "x": 4.429
    },
    {
      "text": "กรณีเป็นกิจการค้าอื่นที่ดำเนินธุรกิจเป็นส่วนตัวให้ระบุสถานที่",
      "y": 5.718,
      "x": 5.618
    },
    {
      "text": "ในห้างหุ้นส่วน หรือกิจการค้าอื่น ๆ ที่ดำเนินธุรกิจเป็นส่วนตัว",
      "y": 5.739,
      "x": 2.081
    },
    {
      "text": "ดำเนินกิจการ พร้อมทั้งภาพถ่ายสถานที่ดำเนินกิจการ สำเนา’",
      "y": 5.928,
      "x": 5.548
    },
    {
      "text": "เช่น หุ้นบุริมสิทธิ หุ้นสามัญ หุ้นกู้ กิจการเลี้ยงสัตว์เพื่อการค้า",
      "y": 5.953,
      "x": 2.09
    },
    {
      "text": "ทะเบียนพาณชย์ (ถ้ามี) และบัญชีรายการทรัพย์สิน(ถ้ามี)",
      "y": 6.144,
      "x": 5.458
    },
    {
      "text": "การลงทุนทางการเกษตร กิจการร้านค้าขายของชำ เป็นต้น",
      "y": 6.165,
      "x": 2.061
    },
    {
      "text": "- กรณีเป็นกิจการเลี้ยงสัตว์เพื่อการค้า การลงทุนทางการเกษตร",
      "y": 6.35,
      "x": 5.624
    },
    {
      "text": "ให้ระบุสถานที่ดำเนินกิจการ พร้อมทั้งภาพถ่ายสถานที่ดำเนิน",
      "y": 6.558,
      "x": 5.544
    },
    {
      "text": "กิจการ และบัญชีรายการทรัพย์สิน หรืออุปกรณ์เครื่องมือ",
      "y": 6.774,
      "x": 5.445
    },
    {
      "text": "ทางการเกษตร เช่น เครื่องสีข้าว เครื่องเพาะกล้า เครื่อง",
      "y": 6.98,
      "x": 5.415
    },
    {
      "text": ": เกี่ยวนวดข้าว เป็นต้น",
      "y": 7.195,
      "x": 4.609
    },
    {
      "text": "หลักฐานอื่นใด ที่แสดงยอดเงินลงทุนคงเหลือ ณ วันที่มีหน้าที่",
      "y": 7.394,
      "x": 5.633
    },
    {
      "text": "แสดงรายการทรัพย์สินและหนี้สิน",
      "y": 7.61,
      "x": 4.91
    },
    {
      "text": "ลับ",
      "y": 11.012,
      "x": 3.996
    }
  ]
}