{
  "doc_name": "วรสิทธิ์_กัลป์ตินันท์_สมาชิกสภาผู้แทนราษฎร_(ส.ส.)_กรณีพ้นจากตำแหน่ง_23_มิ.ย._2566.json",
  "page_number": 5,
  "page_index": 4,
  "total_pages": 34,
  "page_type": "children",
  "is_continuation": false,
  "is_extra_page": false,
  "matched_template_page": null,
  "content": "- ลับ -\nหน้า ๓\nกับเดิร์ • บุตรโดยชอบด้วยกฎหมาย ลำดับที่ ๑-๓ จำนวน ๓ คน\n· บุตรที่เกิดจากบิดามารดาที่มิได้จดทะเบียนสมรส แต่บิดาได้แสดงออก หรือรับรองโดยอุปการะเลี้ยงดู\nให้การศึกษา ดูแลรักษาพยาบาล แสดงออกต่อสังคมไม่ว่าทางตรงหรือทางอ้อมว่าเป็นบุตรของตน\nลำดับที่ ... จำนวน ....... คน\nลำดับ ชื่อ-ชื่อสกุล อายุ ที่อยู่ และ สถานศึกษา / ที่เด็ก เจน\n๑ เด็กหญิงนภวรรณ กัลป์ตินันท์ ที่อยู่ .. * ถนนบูรพาใน อำเภอเมืองอุบลราชธานี\n* ๑๑ จังหวัดอุบลราชธานี\n-สถานศึกษา โรงเรียนอนุบาลอุบลราชธานี\nวัน เดือน ปี เกิด ที่ทำงาน\n๒ เด็กชายพล กัลป์ตินันท์ ที่อยู่: ถนนบูรพาใน อำเภอเมืองอุบลราชธานี\n* ๑๐ จังหวัดอุบลราชธานี\nสถานศึกษา โรงเรียนอนุบาลอุบลราชธานี\nวัน เดือน ปี เกิด ที่ทำงาน\nள เด็กหญิงเพชรพลอย กัลป์ตินันท์ ที่อยู่: นนบูรพาใน อำเภอเมืองอุบลราชธานี\n** ๖ จังหวัดอุบลราชธานี\nสถานศึกษา โรงเรียนอนุบาลอุบลราชธานี\nวัน เดือน ปี เกิด* ที่ทำงาน ใด\n๔ ที่อยู่\n*\nสถานศึกษา\nวัน เดือน ปี เกิด / ที่ทำงาน\n๕ * ที่อยู่ ...\nสถานศึกษา.\nวัน เดือน ปี เกิด* / / ที่ทำงาน\nหมายเหตุ กรณีมีบุตรมากกว่าช่องรายการ ผู้ยื่นบัญชีสามารถจัดทำข้อมูลบุตรเป็นใบแทรกให้ครบทุกคนได้\nลงชื่อ, ผู้ยื่นบัญชี\n- ลับ - ( นายวรสิทธิ์ กัลป์ตินันท์ )",
  "lines": [
    {
      "text": "- ลับ -",
      "y": 0.368,
      "x": 4.22
    },
    {
      "text": "หน้า ๓",
      "y": 0.728,
      "x": 1.09
    },
    {
      "text": "• บุตรโดยชอบด้วยกฎหมาย ลำดับที่ ๑-๓",
      "y": 1.067,
      "x": 3.236
    },
    {
      "text": "กับเดิร์",
      "y": 1.07,
      "x": 1.24
    },
    {
      "text": "จำนวน ๓ คน",
      "y": 1.074,
      "x": 5.117
    },
    {
      "text": "· บุตรที่เกิดจากบิดามารดาที่มิได้จดทะเบียนสมรส แต่บิดาได้แสดงออก หรือรับรองโดยอุปการะเลี้ยงดู",
      "y": 1.304,
      "x": 4.518
    },
    {
      "text": "ให้การศึกษา ดูแลรักษาพยาบาล แสดงออกต่อสังคมไม่ว่าทางตรงหรือทางอ้อมว่าเป็นบุตรของตน",
      "y": 1.528,
      "x": 4.581
    },
    {
      "text": "ลำดับที่ ...",
      "y": 1.718,
      "x": 2.402
    },
    {
      "text": "จำนวน ....... คน",
      "y": 1.74,
      "x": 4.039
    },
    {
      "text": "ลำดับ",
      "y": 2.157,
      "x": 1.232
    },
    {
      "text": "ชื่อ-ชื่อสกุล",
      "y": 2.282,
      "x": 2.843
    },
    {
      "text": "ที่อยู่ และ สถานศึกษา / ที่เด็ก เจน",
      "y": 2.287,
      "x": 6.24
    },
    {
      "text": "อายุ",
      "y": 2.303,
      "x": 4.416
    },
    {
      "text": "*",
      "y": 2.754,
      "x": 5.006
    },
    {
      "text": "เด็กหญิงนภวรรณ กัลป์ตินันท์",
      "y": 2.766,
      "x": 2.525
    },
    {
      "text": "ถนนบูรพาใน อำเภอเมืองอุบลราชธานี",
      "y": 2.807,
      "x": 6.581
    },
    {
      "text": "ที่อยู่ ..",
      "y": 2.847,
      "x": 4.855
    },
    {
      "text": "๑",
      "y": 2.883,
      "x": 1.231
    },
    {
      "text": "๑๑",
      "y": 2.967,
      "x": 4.411
    },
    {
      "text": "*",
      "y": 2.977,
      "x": 4.122
    },
    {
      "text": "จังหวัดอุบลราชธานี",
      "y": 3.033,
      "x": 5.683
    },
    {
      "text": "-สถานศึกษา โรงเรียนอนุบาลอุบลราชธานี",
      "y": 3.271,
      "x": 5.83
    },
    {
      "text": "วัน เดือน ปี เกิด",
      "y": 3.477,
      "x": 1.972
    },
    {
      "text": "ที่ทำงาน",
      "y": 3.5,
      "x": 4.93
    },
    {
      "text": "เด็กชายพล กัลป์ตินันท์",
      "y": 4.088,
      "x": 2.398
    },
    {
      "text": "ถนนบูรพาใน อำเภอเมืองอุบลราชธานี",
      "y": 4.156,
      "x": 6.515
    },
    {
      "text": "ที่อยู่:",
      "y": 4.189,
      "x": 4.846
    },
    {
      "text": "๒",
      "y": 4.209,
      "x": 1.217
    },
    {
      "text": "๑๐",
      "y": 4.281,
      "x": 4.424
    },
    {
      "text": "*",
      "y": 4.322,
      "x": 4.117
    },
    {
      "text": "จังหวัดอุบลราชธานี",
      "y": 4.383,
      "x": 5.596
    },
    {
      "text": "สถานศึกษา โรงเรียนอนุบาลอุบลราชธานี",
      "y": 4.613,
      "x": 5.87
    },
    {
      "text": "วัน เดือน ปี เกิด",
      "y": 4.821,
      "x": 1.957
    },
    {
      "text": "ที่ทำงาน",
      "y": 4.843,
      "x": 4.93
    },
    {
      "text": "เด็กหญิงเพชรพลอย กัลป์ตินันท์",
      "y": 5.428,
      "x": 2.594
    },
    {
      "text": "นนบูรพาใน อำเภอเมืองอุบลราชธานี",
      "y": 5.484,
      "x": 6.5
    },
    {
      "text": "ที่อยู่:",
      "y": 5.531,
      "x": 4.848
    },
    {
      "text": "ள",
      "y": 5.554,
      "x": 1.211
    },
    {
      "text": "๖",
      "y": 5.616,
      "x": 4.357
    },
    {
      "text": "**",
      "y": 5.652,
      "x": 4.104
    },
    {
      "text": "จังหวัดอุบลราชธานี",
      "y": 5.692,
      "x": 5.581
    },
    {
      "text": "สถานศึกษา โรงเรียนอนุบาลอุบลราชธานี",
      "y": 5.934,
      "x": 5.841
    },
    {
      "text": "วัน เดือน ปี เกิด*",
      "y": 6.153,
      "x": 1.961
    },
    {
      "text": "ที่ทำงาน ใด",
      "y": 6.162,
      "x": 5.062
    },
    {
      "text": "ที่อยู่",
      "y": 6.867,
      "x": 4.82
    },
    {
      "text": "๔",
      "y": 6.879,
      "x": 1.217
    },
    {
      "text": "*",
      "y": 7.034,
      "x": 4.107
    },
    {
      "text": "สถานศึกษา",
      "y": 7.309,
      "x": 4.997
    },
    {
      "text": "วัน เดือน ปี เกิด",
      "y": 7.493,
      "x": 1.961
    },
    {
      "text": "/",
      "y": 7.497,
      "x": 2.712
    },
    {
      "text": "ที่ทำงาน",
      "y": 7.511,
      "x": 4.92
    },
    {
      "text": "ที่อยู่ ...",
      "y": 8.199,
      "x": 4.863
    },
    {
      "text": "๕",
      "y": 8.207,
      "x": 1.213
    },
    {
      "text": "*",
      "y": 8.317,
      "x": 4.096
    },
    {
      "text": "สถานศึกษา.",
      "y": 8.639,
      "x": 5.002
    },
    {
      "text": "วัน เดือน ปี เกิด*",
      "y": 8.825,
      "x": 1.967
    },
    {
      "text": "/",
      "y": 8.834,
      "x": 2.69
    },
    {
      "text": "/",
      "y": 8.839,
      "x": 3.384
    },
    {
      "text": "ที่ทำงาน",
      "y": 8.843,
      "x": 4.915
    },
    {
      "text": "หมายเหตุ กรณีมีบุตรมากกว่าช่องรายการ ผู้ยื่นบัญชีสามารถจัดทำข้อมูลบุตรเป็นใบแทรกให้ครบทุกคนได้",
      "y": 9.577,
      "x": 3.807
    },
    {
      "text": "ลงชื่อ,",
      "y": 10.852,
      "x": 4.127
    },
    {
      "text": "ผู้ยื่นบัญชี",
      "y": 10.887,
      "x": 6.976
    },
    {
      "text": "( นายวรสิทธิ์ กัลป์ตินันท์ )",
      "y": 11.065,
      "x": 5.487
    },
    {
      "text": "- ลับ -",
      "y": 11.094,
      "x": 4.164
    }
  ]
}